ypcc/__init__.py
ypcc2/__init__.py
super_combiright-0.7.1.dist-info/LICENSE
super_combiright-0.7.1.dist-info/METADATA
super_combiright-0.7.1.dist-info/WHEEL
super_combiright-0.7.1.dist-info/top_level.txt
super_combiright-0.7.1.dist-info/RECORD
