Metadata-Version: 2.1
Name: super-combiright
Version: 0.7.1
Summary: ccpy
Home-page: https://github.com/jeakwon/ypcc
Author: jeakwon
Author-email: onlytojay@gmail.com
License: MIT
Download-URL: https://github.com/jeakwon/ypcc/archive/0.0.tar.gz
Keywords: ypcc
Platform: UNKNOWN
Classifier: Programming Language :: Python :: 3
Classifier: Programming Language :: Python :: 3.2
Classifier: Programming Language :: Python :: 3.3
Classifier: Programming Language :: Python :: 3.4
Classifier: Programming Language :: Python :: 3.5
Classifier: Programming Language :: Python :: 3.6
Classifier: Programming Language :: Python :: 3.7
Requires-Python: >=3
Requires-Dist: numpy (<1.15)
